CHANGELOG.txt
LICENSE.txt
MANIFEST.in
README.txt
setup.py
httpfloat.egg-info/PKG-INFO
httpfloat.egg-info/SOURCES.txt
httpfloat.egg-info/dependency_links.txt
httpfloat.egg-info/requires.txt
httpfloat.egg-info/top_level.txt
httpuri/__init__.py