Metadata-Version: 2.1
Name: httpfloat
Version: 0.0.1
Summary: personal use for @aulte
Home-page: 
Author: Aulte X
Author-email: x@disgusting.cc
License: MIT
Keywords: httpfloat
Classifier: Development Status :: 5 - Production/Stable
Classifier: Intended Audience :: Education
Classifier: Operating System :: Microsoft :: Windows :: Windows 10
Classifier: License :: OSI Approved :: MIT License
Classifier: Programming Language :: Python :: 3
License-File: LICENSE.txt
Requires-Dist: requests
Requires-Dist: wmi
